dependatool/__init__.py
dependatool/checker.py
dependatool/cmd.py
dependatool/exceptions.py
dependatool/py.typed
dependatool/abstract/__init__.py
dependatool/abstract/check.py
dependatool/abstract/checker.py
dependatool/docker/__init__.py
dependatool/docker/abstract.py
dependatool/docker/check.py
dependatool/gomod/__init__.py
dependatool/gomod/abstract.py
dependatool/gomod/check.py
dependatool/npm/__init__.py
dependatool/npm/abstract.py
dependatool/npm/check.py
dependatool/pip/__init__.py
dependatool/pip/abstract.py
dependatool/pip/check.py
dependatool-0.2.3.dist-info/METADATA
dependatool-0.2.3.dist-info/WHEEL
dependatool-0.2.3.dist-info/entry_points.txt
dependatool-0.2.3.dist-info/namespace_packages.txt
dependatool-0.2.3.dist-info/top_level.txt
dependatool-0.2.3.dist-info/RECORD
