Metadata-Version: 2.1
Name: dependatool
Version: 0.2.3
Summary: "Pip dependabot checker used in Envoy proxy's CI"
Home-page: https://github.com/envoyproxy/toolshed/tree/main/dependatool
Author: Ryan Northey
Author-email: ryan@synca.io
Maintainer: Ryan Northey
Maintainer-email: ryan@synca.io
License: Apache Software License 2.0
Requires-Python: >=3.10.0
Requires-Dist: abstracts (>=0.0.12)
Requires-Dist: aio.core (>=0.10.1)
Requires-Dist: aio.run.checker (>=0.5.7)
